npdep_common/__init__.py
npdep_common/__main__.py
npdep_common/args/Args.py
npdep_common/args/__init__.py
npdep_common/interface/Interface.py
npdep_common/interface/__init__.py
npdep_common/loader/Loader.py
npdep_common/loader/__init__.py
npdep_common/output/Output.py
npdep_common/output/__init__.py
npdep_common/util/Util.py
npdep_common/util/__init__.py
npdep_common-1.0.0.dist-info/METADATA
npdep_common-1.0.0.dist-info/WHEEL
npdep_common-1.0.0.dist-info/entry_points.txt
npdep_common-1.0.0.dist-info/top_level.txt
npdep_common-1.0.0.dist-info/RECORD
