Metadata-Version: 2.1
Name: npdep_common
Version: 1.0.0
Summary: Common dependencies for NPDEP
Home-page: https://github.com/npdep/npdep-common
Author: npdep
Classifier: Operating System :: OS Independent 
Classifier: Programming Language :: Python :: 3 
